openarmx_arm_driver/__init__.py
openarmx_arm_driver/arm.py
openarmx_arm_driver/exceptions.py
openarmx_arm_driver/robot.py
openarmx_arm_driver/_lib/__init__.py
openarmx_arm_driver/_lib/can_comm.cpython-39-x86_64-linux-gnu.so
openarmx_arm_driver/_lib/can_utils.cpython-39-x86_64-linux-gnu.so
openarmx_arm_driver/_lib/log_utils.cpython-39-x86_64-linux-gnu.so
openarmx_arm_driver/_lib/motor_config_loader.cpython-39-x86_64-linux-gnu.so
openarmx_arm_driver/_lib/motor_control.cpython-39-x86_64-linux-gnu.so
openarmx_arm_driver/_lib/motor_manager.cpython-39-x86_64-linux-gnu.so
openarmx_arm_driver/config/__init__.py
openarmx_arm_driver/config/arm_direction_config.yaml
openarmx_arm_driver/config/motor_config.yaml
openarmx_arm_driver-1.1.10.dist-info/licenses/LICENSE
openarmx_arm_driver-1.1.10.dist-info/METADATA
openarmx_arm_driver-1.1.10.dist-info/WHEEL
openarmx_arm_driver-1.1.10.dist-info/top_level.txt
openarmx_arm_driver-1.1.10.dist-info/RECORD
